[
  {
    "question": "พิจารณาภาพที่กำหนดซึ่งแสดงภาชนะทรงสี่เหลี่ยมมุมฉากฐานสี่เหลี่ยมด้านขนานใส่น้ำสูง 3 ซม. เพื่อให้ได้ความจุเท่ากับ 360 ลูกบาศก์เซนติเมตร ถ้าส่วนสูงเป็น 3 เท่าของด้านกว้าง และด้านยาวยาวกว่าด้านกว้าง 3 ซม. ต้องการหาความยาวด้านกว้างของภาชนะ",
    "choices": ["6 ซม.", "8 ซม.", "10 ซม.", "12 ซม."],
    "correct_answer": "6 ซม."
  },
  {
    "question": "เครื่องคิดเลขคำนวณราคาสินค้านำเข้าจากราคาสินค้า 2,985,000 บาท โดยมีอัตราภาษีนำเข้า 42.60% และราคาสุทธิคือภาษีมูลค่าเพิ่ม 7% ต้องการหาภาษีมูลค่าเพิ่มที่ต้องจ่าย",
    "choices": ["2.827 × 10^5 บาท", "2.827 × 10^6 บาท", "2.986 × 10^6 บาท", "5.895 × 10^6 บาท"],
    "correct_answer": "2.827 × 10^5 บาท"
  },
  {
    "question": "โรงเรียนขายบัตรเข้าชมงานกีฬา โดยบัตรเข้าชมมี 2 แบบคือ แบบธรรมดาราคา 20 บาท และแบบพิเศษราคา 22 บาท ถ้าขายบัตรรวมได้ 120 ใบ และได้เงินรวม 2,620 บาท ต้องการหาจำนวนบัตรพิเศษที่ขายได้",
    "image": "assets/images/math2566M3/3.png",
    "choices": ["1920 บาท", "2260 บาท", "2928 บาท", "3520 บาท"],
    "correct_answer": "2260 บาท"
  },
  {
    "question": "ตามรูป กำหนดสมการพาราโบลา มีจุดยอดที่ (0,0) และแกนสมมาตรคือแกน y ความกว้างฐาน 4 เมตร และสูงสุด 3 เมตร ถ้าต้องการสร้างซุ้มประตูโค้ง ต้องการหาความสูงที่ระดับกว้าง 2 เมตร",
    "image": "assets/images/math2566M3/4.png",
    "choices": ["1.5 เมตร", "2 เมตร", "2.5 เมตร", "3 เมตร"],
    "correct_answer": "2 เมตร"
  },
  {
    "question": "จากการสอบถามนักเรียนจำนวน 3,060 คนที่โรงอาหาร พบว่า มีการบริโภคอาหารประเภทต่าง ๆ ดังนี้: เนื้อ 48.6%, หมู 22.4%, ปลา 18%, ไก่ 10.6%, กุ้ง 0.9%. ต้องการหาจำนวนคนที่บริโภคเนื้อ",
    "image": "assets/images/math2566M3/5.png",
    "choices": ["354 คน", "495 คน", "552 คน", "619 คน"],
    "correct_answer": "1487 คน"
  },
  {
    "question": "ถ้านำเงินบาทไทยไปซื้อเงินดอลลาร์สหรัฐ แล้วข้อใดกล่าวถูกต้อง",
    "image": "assets/images/math2566M3/6.png",
    "choices": ["ถ้าซื้อในวันที่ 5 ส.ค. แล้วขายคืนก่อนวันที่ 2 ก.ย. จะไม่ขาดทุนอย่างแน่นอน", "ถ้าซื้อในวันที่ 8 ก.ค. แล้วขายคืนช่วงวันที่ 10 - 19 ส.ค. จะได้กำไรอย่างแน่นอน", "ถ้าซื้อในช่วงวันที่ 5 - 19 ส.ค. แล้วไปขายคืนช่วงวันที่ 2 - 16 ก.ย. จะได้กำไรอย่างแน่นอน", "ถ้าซื้อในช่วงวันที่ 8 - 22 ก.ค. แล้วไปขายคืนช่วงวันที่ 19 ส.ค. - 2 ก.ย.จะขาดทุนอย่างแน่นอน"],
    "correct_answer": "ถ้าซื้อในวันที่ 8 ก.ค. แล้วขายคืนช่วงวันที่ 10 - 19 ส.ค. จะได้กำไรอย่างแน่นอน"
  },
  {
    "question": "ในการทำนมชนิดหนึ่งต้องใช้เมนกล่องรสหวานจำนวนมากกว่ามนกล่องรสจืด 15 กล่อง ถ้าค่าเฉลี่ยของจำนวนเมนกล่องทั้ง 2 ชนิด คือ 28.5 กล่อง แล้วต้องใช้เมนกล่องรสจืดในการทำนมทั้งหมดกี่กล่อง",
    "choices": ["13.5 กล่อง", "21 กล่อง", "21.75 กล่อง", "43.5 กล่อง"],
    "correct_answer": "21 กล่อง"
  },
  {
    "question": "ถ้าต้องการทำบัตรคอนเสิร์ตจำนวน 1,000 ใบ โดยแต่ละใบมีขนาด กว้าง 5 เซนติเมตร และยาว 15 เซนติเมตร ซึ่งจัดตัดจากกระดาษโปสเตอร์แผ่นใหญ่ขนาด กว้าง 50 เซนติเมตร และยาว 90 เซนติเมตร แล้วจะต้องซื้อกระดาษโปสเตอร์จากร้านค้า มาใช้อย่างน้อยที่สุดกี่แผ่น (ร้านค้าจะไม่ตัดแบ่งกระดาษขาย)",
    "choices": ["16 แผ่น", "17 แผ่น", "60 แผ่น", "75 แผ่น"],
    "correct_answer": "17 แผ่น"
  },
  {
    "question": "นักเรียนกลุ่มหนึ่งเขียนโครงงานคณิตศาสตร์ออกแบบบันไดสำเร็จรูปด้วยการนำแท่งคอนกรีตมาประกอบกัน โดยแต่ละแท่งเป็นคอนกรีตรงสี่เหลี่ยมมุมฉาก กว้าง 8 นิ้ว ยาว 21 นิ้ว และสูง 8 นิ้ว ด้านในเป็นรูปทรงกระบอกกลวงมีระยะห่างจากขอบ a นิ้ว ถ้า 1 แท่งใช้คอนกรีตหล่อทั้งหมด 750 ลูกบาศก์นิ้ว แล้วรัศมีของทรงกระบอกยาวกี่นิ้ว (กำหนด π = 22/7)",
    "image": "assets/images/math2566M3/9.png",
    "choices": ["2 นิ้ว", "3 นิ้ว", "4 นิ้ว", "6 นิ้ว"],
    "correct_answer": "3 นิ้ว"
  },
  {
    "question": "โรงเรียนต้องการสร้างกระโจมแปลงเกษตรทรงพีระมิดฐานจตุรัส มีความสูงเท่ากับความกว้างของฐาน ด้านในมีท่อน้ำเพื่อติดระบบรดน้ำอัตโนมัติ ติดตรงกลางและสูงครึ่งหนึ่งของกระโจม ดังรูป ถ้าใช้วัสดุสำหรับสร้างกระโจม 25√5 ตารางเมตร (ไม่รวมฐานที่เป็นพื้นดิน) แล้วท่อน้ำสูงกี่เมตร",
    "image": "assets/images/math2566M3/10.png",
    "choices": ["1.5 เมตร", "1.8 เมตร", "2.2 เมตร", "2.5 เมตร"],
    "correct_answer": "2.2 เมตร"
  },
  {
    "question": "ถ้าระยะทางจากบ้านแอน ไปยังโรงเรียนมากกว่า 4 เท่าของระยะทางจากบ้านน้อยไปยังโรงเรียน 200 เมตร และบ้านแคทห่างจากวัดเพียง 420 เมตร แล้วบ้านแอนห่างจากวัดกี่กิโลเมตร",
    "image": "assets/images/math2566M3/11.png",
    "choices": ["1.48 กิโลเมตร", "1.68 กิโลเมตร", "1.70 กิโลเมตร", "1.88 กิโลเมตร"],
    "correct_answer": "1.68 กิโลเมตร"
  },
  {
    "question": "นาฬิกากรงล้อมเรือนหนึ่งมีเข็มวินาที ยาว 7 เซนติเมตร โดยเข็มวินาทีที่เคลื่อนที่หมุนแบบต่อเนื่อง เมื่อเวลาผ่านไป 4 นาที จุดตรงปลายเข็มวินาทีที่ละหมุนเป็นระยะทางประมาณกี่เซนติเมตร (กำหนด π = 22/7)",
    "choices": ["22 เซนติเมตร", "44 เซนติเมตร", "88 เซนติเมตร", "176 เซนติเมตร"],
    "correct_answer": "176 เซนติเมตร"
  },
  {
    "question": "บันไดวางพาดกำแพงโดยทำมุม 30 องศากับผนังกำแพงในแนวดิ่ง ถ้าบันไดยาว 6 เมตร แล้วปลายอีกด้านของบันไดอยู่ห่างจากฐานกำแพงกี่เมตร",
    "choices": ["3 เมตร", "3√2 เมตร", "3√3 เมตร", "6 เมตร"],
    "correct_answer": "3 เมตร"
  },
  {
    "question": "จากข้อมูลข้างต้น พื้นที่ของรูปสามเหลี่ยม TRP มีขนาดกี่ตารางเซนติเมตร (RS = 5, SP = 4 และ QS = 8)",
    "image": "assets/images/math2566M3/14.png",
    "choices": ["20.25 ตารางเซนติเมตร", "45 ตารางเซนติเมตร", "50.63 ตารางเซนติเมตร", "81 ตารางเซนติเมตร"],
    "correct_answer": "45 ตารางเซนติเมตร"
  },
  {
    "question": "นักเรียนที่อยู่ชมรมรักโรงเรียนกลุ่มหนึ่ง มีอายุ 9, 12, 10, 14 ปี และมีเพื่อนอีก 3 คน รวมอยู่ด้วย ถ้าอายุเฉลี่ยของนักเรียนกลุ่มนี้ เท่ากับ 12 ปี ดังนั้นมัธยฐานของอายุนักเรียนทั้ง 7 คน เท่ากับข้อใด",
    "choices": ["9 ปี", "9.5 ปี", "13 ปี", "14 ปี"],
    "correct_answer": "12 ปี"
  },
  {
    "question": "เด็กหญิง JANE ซื้อขนมปังมา 1 กล่อง ในกล่องเป็นขนมปังที่เป็นรูปตัวอักษรภาษาอังกฤษ A - Z ครบทั้ง 26 ตัวอักษร แต่ละตัวอักษรจะมีจำนวน 5 ชิ้น เท่าๆ กัน เมื่อเปิดกล่องแล้วเด็กหญิง JANE หยิบขนมปังในกล่องขึ้นเป็นครั้งแรกจำนวน 1 ชิ้น ผลลัพธ์ของความน่าจะเป็นที่จะหยิบได้ตัวอักษรที่อยู่ในชื่อกับหยิบไม่ได้ตัวอักษรที่อยู่ในชื่อของตนเองเป็นเท่าใด",
    "choices": ["2/13", "4/13", "9/13", "11/13"],
    "correct_answer": "4/13"
  },
  {
    "question": "โจทย์: √(144x^10 y^2 z^9) × √(9x^-2 y^-2 z^-5) / √(36x^9 y^8 z^4) มีค่าเท่าใด",
    "choices": ["x z^2 / y^3", "2x z^2 / y^3", "x^2 z^2 / y^2", "2x^2 z / y^3"],
    "correct_answer": "2x z^2 / y^3"
  },
  {
    "question": "สมใจเล่นเกมทายตัวเลขกับเพื่อน โดยสมใจจะเลือกจำนวนสองจำนวน แล้วบอกคำใบ้ที่เกี่ยวกับจำนวนทั้งสองให้แก่เพื่อน ถ้าสมใจบอกว่าสองเท่าของจำนวนน้อยมีค่ามากกว่าจำนวนมากอยู่ 8 และสองเท่าของจำนวนมากมีค่ามากกว่าสามเท่าของจำนวนน้อยอยู่ 2 แล้วผลบวกของจำนวนทั้งสองมีค่าเท่าใด",
    "choices": ["24", "26", "28", "30"],
    "correct_answer": "28"
  },
  {
    "question": "กำหนดให้ PQR เป็นรูปสามเหลี่ยมที่มีมุม R เป็นมุมฉาก มีด้าน QR ยาว 10√3 หน่วย และด้าน PQ ยาว 20 หน่วย ถ้าลากเส้นตรงจากจุด Q ไปตั้งฉากกับด้าน PQ ที่จุด S แล้ว √3 ของความยาวของเส้น RS มีค่าเท่าใด",
    "choices": ["5", "10", "15", "20"],
    "correct_answer": "10"
  },
  {
    "question": "จากการสำรวจคะแนนสอบวิชาคณิตศาสตร์ของนักเรียน 3 คน พบว่า ค่ามัธยฐานของคะแนนสอบของนักเรียนทั้ง 3 คน เท่ากับ 67 คะแนน มีเลขศูนย์ เท่ากับ 65 คะแนน และพิสัย เท่ากับ 18 คะแนน อยากทราบว่านักเรียนที่ได้คะแนนต่ำสุดได้คะแนนเท่าใด",
    "choices": ["56", "57", "58", "59"],
    "correct_answer": "56"
  }
]
